pys3fuse/__init__.py
pys3fuse/__main__.py
pys3fuse/cli/__init__.py
pys3fuse/cli/cli.py
pys3fuse/cli/config_cmd.py
pys3fuse/cli/mount_cmd.py
pys3fuse/core/__init__.py
pys3fuse/core/config.py
pys3fuse/core/exceptions.py
pys3fuse/core/log_config.py
pys3fuse/core/schemas.py
pys3fuse/core/utils.py
pys3fuse/filesystem.py
pys3fuse/s3service.py
pys3fuse/sync.py
pys3fuse-0.6.1.dist-info/METADATA
pys3fuse-0.6.1.dist-info/WHEEL
pys3fuse-0.6.1.dist-info/RECORD
